odoo/addons/account_menu/README.rst
odoo/addons/account_menu/__init__.py
odoo/addons/account_menu/__manifest__.py
odoo/addons/account_menu/demo/res_groups.xml
odoo/addons/account_menu/i18n/account_menu.pot
odoo/addons/account_menu/i18n/fa.po
odoo/addons/account_menu/i18n/fa_IR.po
odoo/addons/account_menu/i18n/fr.po
odoo/addons/account_menu/i18n/sk_SK.po
odoo/addons/account_menu/models/__init__.py
odoo/addons/account_menu/models/account_group.py
odoo/addons/account_menu/models/account_tag.py
odoo/addons/account_menu/models/account_tax_group.py
odoo/addons/account_menu/readme/CONFIGURE.rst
odoo/addons/account_menu/readme/CONTRIBUTORS.rst
odoo/addons/account_menu/readme/DESCRIPTION.rst
odoo/addons/account_menu/static/description/icon.png
odoo/addons/account_menu/static/description/index.html
odoo/addons/account_menu/views/menu.xml
odoo/addons/account_menu/views/view_account_account_template.xml
odoo/addons/account_menu/views/view_account_bank_statement.xml
odoo/addons/account_menu/views/view_account_chart_template.xml
odoo/addons/account_menu/views/view_account_fiscal_position_template.xml
odoo/addons/account_menu/views/view_account_group.xml
odoo/addons/account_menu/views/view_account_move_line.xml
odoo/addons/account_menu/views/view_account_tag.xml
odoo/addons/account_menu/views/view_account_tax_group.xml
odoo/addons/account_menu/views/view_account_tax_template.xml
odoo/addons/account_menu/views/view_account_type.xml
odoo13_addon_account_menu-13.0.1.0.1.dist-info/METADATA
odoo13_addon_account_menu-13.0.1.0.1.dist-info/WHEEL
odoo13_addon_account_menu-13.0.1.0.1.dist-info/top_level.txt
odoo13_addon_account_menu-13.0.1.0.1.dist-info/RECORD
